evescout/__init__.py
evescout/admin.py
evescout/app_settings.py
evescout/apps.py
evescout/auth_hooks.py
evescout/evescout.py
evescout/models.py
evescout/tasks.py
evescout/utils.py
evescout/cogs/evescout.py
evescout/cogs/utils/__init__.py
evescout/cogs/utils/autocompletes.py
evescout/cogs/utils/region_obs.py
evescout/management/commands/evescout_load_system.py
evescout/management/commands/evescout_update_signatures.py
evescout/migrations/0001_initial.py
evescout/migrations/0002_alter_signaturepinger_ping_type.py
evescout/migrations/0003_signaturepinger_ping_everyone_under_distance_jump_and_more.py
evescout/migrations/__init__.py
evescout/tests/__init__.py
evescout/tests/test_pinger.py
evescout/tests/test_signatures.py
evescout/tests/test_tasks.py
evescout/tests/testdata/README.md
evescout/tests/testdata/__init__.py
evescout/tests/testdata/create_eveuniverse.py
evescout/tests/testdata/eveuniverse.json
evescout/tests/testdata/load_eveuniverse.py
aa_evescout-1.2.0.dist-info/licenses/LICENSE
aa_evescout-1.2.0.dist-info/WHEEL
aa_evescout-1.2.0.dist-info/METADATA
aa_evescout-1.2.0.dist-info/RECORD
